comfoairq_homie/__init__.py
comfoairq_homie/__main__.py
comfoairq_homie/comfoairq_homie.py
comfoairq_homie/comfoairq/__init__.py
comfoairq_homie/comfoairq/comfoairq.py
comfoairq_homie/comfoairq/comfoairq_const.py
comfoairq_homie/homie_device/__init__.py
comfoairq_homie/homie_device/comfoairq_transformations.py
comfoairq_homie/homie_device/device_comfoairq.py
comfoairq_homie/homie_device/device_comfoairq_gateway.py
comfoairq_homie-0.6.2.dist-info/LICENSE
comfoairq_homie-0.6.2.dist-info/METADATA
comfoairq_homie-0.6.2.dist-info/WHEEL
comfoairq_homie-0.6.2.dist-info/entry_points.txt
comfoairq_homie-0.6.2.dist-info/top_level.txt
comfoairq_homie-0.6.2.dist-info/RECORD
