Metadata-Version: 2.1
Name: comfoairq-homie
Version: 0.6.2
Summary: Homie4 for Zehnder ComfoAirQ
Home-page: https://github.com/klaudiusz223/ComfoAirQ-Homie
Author: Klaudiusz
Author-email: klaudiusz223@users.noreply.github.com
License: UNKNOWN
Platform: UNKNOWN
Classifier: Programming Language :: Python :: 3
Classifier: License :: OSI Approved :: MIT License
Classifier: Operating System :: OS Independent
Requires-Python: >=3.6
Requires-Dist: Homie4 (>=0.3.2)
Requires-Dist: pycomfoconnect (>=0.4)
Requires-Dist: pyyaml
